unionstation/__init__.py
unionstation/core/__init__.py
unionstation/core/aws_utils.py
unionstation/core/drivers.py
unionstation-0.1.0.dist-info/WHEEL
unionstation-0.1.0.dist-info/METADATA
unionstation-0.1.0.dist-info/RECORD
