Metadata-Version: 2.1
Name: unionstation
Version: 0.1.0
Summary: Big ML/DL dataset processing station
Author: H-AI
Author-email: dongjian413@gmail.com
Requires-Python: >=3.7,<4.0
Classifier: Programming Language :: Python :: 3
Classifier: Programming Language :: Python :: 3.7
Classifier: Programming Language :: Python :: 3.8
Classifier: Programming Language :: Python :: 3.9
Requires-Dist: absl-py (==0.10.0)
Requires-Dist: betterproto[compiler] (>=2.0.0b1,<3.0.0)
Requires-Dist: boto3 (>=1.14.44,<2.0.0)
Requires-Dist: opencv-python (==4.2.0.34)
Requires-Dist: pandas (>=1.1.1,<2.0.0)
Requires-Dist: protobuf (>=3.13.0,<4.0.0)
Requires-Dist: pyarrow (>=1.0.0,<2.0.0)
Requires-Dist: pycocotools (>=2.0.1,<3.0.0)
Requires-Dist: pyspark (>=3.0.0,<4.0.0)
Requires-Dist: s3fs (>=0.4.2,<0.5.0)
Requires-Dist: tabulate (>=0.8.7,<0.9.0)
Requires-Dist: tqdm (>=4.48.2,<5.0.0)
Requires-Dist: urllib3 (>=1.25.10,<2.0.0)
